siliconsuite_symbol_generator-1.4.1.dist-info/licenses/LICENSE
symbol_generator/__init__.py
symbol_generator/default_theme.yaml
symbol_generator/font_character_widths.py
symbol_generator/generate_font_charachter_widths.py
symbol_generator/symbol.drawio.j2
symbol_generator/symbol.svg.j2
symbol_generator/symbol_generator.py
siliconsuite_symbol_generator-1.4.1.dist-info/METADATA
siliconsuite_symbol_generator-1.4.1.dist-info/WHEEL
siliconsuite_symbol_generator-1.4.1.dist-info/entry_points.txt
siliconsuite_symbol_generator-1.4.1.dist-info/top_level.txt
siliconsuite_symbol_generator-1.4.1.dist-info/RECORD
