Metadata-Version: 2.4
Name: siliconsuite-symbol-generator
Version: 1.4.1
Summary: Generate symbol schematics for hardware IP cores.
License: MIT
Project-URL: Homepage, https://github.com/Louis-DR/SiliconSuite-SymbolGenerator
Classifier: Programming Language :: Python :: 3
Classifier: Operating System :: OS Independent
Requires-Python: >=3.8
License-File: LICENSE
Requires-Dist: j2gpp>=3.1
Requires-Dist: PyYAML>=6.0
Dynamic: license-file
